SmartsheetFunctions/__init__.py
SmartsheetFunctions/smartsheet.py
SmartsheetFunctions-0.0.5.5.dist-info/LICENSE
SmartsheetFunctions-0.0.5.5.dist-info/METADATA
SmartsheetFunctions-0.0.5.5.dist-info/WHEEL
SmartsheetFunctions-0.0.5.5.dist-info/top_level.txt
SmartsheetFunctions-0.0.5.5.dist-info/RECORD
