Metadata-Version: 2.1
Name: SmartsheetFunctions
Version: 0.0.5.5
Summary: SmartSheet Functions for development
Author: Derek Bantel
Author-email: derekbantel@outlook.com
License: MIT
Classifier: Programming Language :: Python :: 3
Classifier: License :: OSI Approved :: MIT License
Classifier: Operating System :: OS Independent
License-File: LICENSE
Requires-Dist: requests
